<wpml-config>
  <custom-types>
    <custom-type translate="1">portfolio</custom-type>
  </custom-types>
  <taxonomies>
    <taxonomy translate="1">portfolio_category</taxonomy>
  </taxonomies>
  <admin-texts>
    <key name="withemes_header_text"/>
  </admin-texts>
  <shortcodes>
    <shortcode>
            <tag>button</tag>
            <attributes>
                <attribute>text</attribute>
                <attribute>link</attribute>
            </attributes>
        </shortcode>
  </shortcodes>
</wpml-config>

